appscriptify/__init__.py
appscriptify/__main__.py
appscriptify/appscriptify.py
appscriptify/templates/login/.env
appscriptify/templates/login/LICENCE
appscriptify/templates/login/README.md
appscriptify/templates/login/app.py
appscriptify/templates/login/config.json
appscriptify/templates/login/database.py
appscriptify/templates/login/requirements.txt
appscriptify/templates/login/__pycache__/database.cpython-313.pyc
appscriptify/templates/login/static/css/login.css
appscriptify/templates/login/static/css/signup.css
appscriptify/templates/login/static/js/login.js
appscriptify/templates/login/static/js/signup.js
appscriptify/templates/login/templates/login.html
appscriptify/templates/login/templates/signup.html
appscriptify-1.2.0.dist-info/licenses/LICENSE
appscriptify-1.2.0.dist-info/METADATA
appscriptify-1.2.0.dist-info/WHEEL
appscriptify-1.2.0.dist-info/entry_points.txt
appscriptify-1.2.0.dist-info/top_level.txt
appscriptify-1.2.0.dist-info/RECORD
