Metadata-Version: 2.4
Name: appscriptify
Version: 1.2.0
Summary: AppScriptify CLI — create app templates instantly
Home-page: https://appscriptify.com
Author: Vansh Choyal
License: MIT
Requires-Python: >=3.6
License-File: LICENSE
Dynamic: author
Dynamic: description
Dynamic: description-content-type
Dynamic: home-page
Dynamic: license
Dynamic: license-file
Dynamic: requires-python
Dynamic: summary
